{
  "entities": [
    {"id": "entity:git-pr", "text": "GitHub Pull Request 工作流 — 创建分支、提交代码、发起 PR、代码审查、合并", "energy": 0.8, "source": "seed", "pinned": true, "dna": {}},
    {"id": "entity:git-auth", "text": "GitHub 认证配置 — SSH key 设置、Personal Access Token 生成、git config 全局配置", "energy": 0.7, "source": "seed", "pinned": true, "dna": {}},
    {"id": "entity:git-issues", "text": "GitHub Issues 管理 — 创建 issue、标签分类、里程碑追踪、关闭 issue 的 commit 关联", "energy": 0.6, "source": "seed", "pinned": false, "dna": {}},
    {"id": "entity:git-review", "text": "Code Review 最佳实践 — Review checklist、Comments 规范、Approve/Request Changes 流程", "energy": 0.7, "source": "seed", "pinned": true, "dna": {}},
    {"id": "entity:wsl-setup", "text": "WSL 环境配置 — 安装发行版、切换默认版本、设置内存限制、启用 systemd", "energy": 0.8, "source": "seed", "pinned": true, "dna": {}},
    {"id": "entity:wsl-network", "text": "WSL 网络调试 — /etc/resolv.conf 修复、代理配置、端口转发、Windows 防火墙规则", "energy": 0.7, "source": "seed", "pinned": false, "dna": {}},
    {"id": "entity:wsl-bridge", "text": "WSL 与 Windows 双向访问 — 文件共享 /mnt/ 挂载、Windows EXE 调用、VcXsrv X11 转发", "energy": 0.6, "source": "seed", "pinned": false, "dna": {}},
    {"id": "entity:tdd-core", "text": "测试驱动开发 — 红绿重构循环：先写失败测试 → 写最少代码通过 → 重构优化", "energy": 0.8, "source": "seed", "pinned": true, "dna": {}},
    {"id": "entity:tdd-pytest", "text": "Pytest 测试框架 — fixture 管理、parametrize 参数化、conftest 共享配置、覆盖率报告", "energy": 0.7, "source": "seed", "pinned": false, "dna": {}},
    {"id": "entity:dna-extract", "text": "DNA 信号提取 — 字符级脚本隔离分词、4链留存(domain/entity/pattern/context)、无词表不分类", "energy": 0.9, "source": "seed", "pinned": true, "dna": {}},
    {"id": "entity:dna-match", "text": "DNA 磁吸匹配 — coordinate_resonance 三级共振(字符/子串/精确)、实时从text提取信号", "energy": 0.9, "source": "seed", "pinned": true, "dna": {}},
    {"id": "entity:dna-wormhole", "text": "虫洞展开联想 — 种子实体的DNA信号独立激发磁吸、固定能量0.7、1跳保证精度", "energy": 0.9, "source": "seed", "pinned": true, "dna": {}},
    {"id": "entity:python-package", "text": "Python 包构建 — pyproject.toml 配置、setuptools 打包、pip install -e 本地安装", "energy": 0.6, "source": "seed", "pinned": false, "dna": {}},
    {"id": "entity:python-lint", "text": "Python 代码规范 — ruff/flake8 检查、black 格式化、类型注解 mypy、pre-commit hooks", "energy": 0.5, "source": "seed", "pinned": false, "dna": {}},
    {"id": "entity:debug-agent", "text": "AI Agent 调试方法论 — 分步检查输入/输出、隔离变量、二分法定位、日志插桩", "energy": 0.7, "source": "seed", "pinned": true, "dna": {}},
    {"id": "entity:debug-terminal", "text": "终端调试工具 — strace 系统调用追踪、htop 资源监控、netstat 端口检查、journalctl 日志", "energy": 0.6, "source": "seed", "pinned": false, "dna": {}},
    {"id": "entity:gpu-cost", "text": "GPU 成本优化 — 端脑云/AutoDL/恒源云对比、按需实例 vs 竞价实例、存储与计算分离", "energy": 0.7, "source": "seed", "pinned": true, "dna": {}},
    {"id": "entity:gpu-deploy", "text": "GPU 部署流程 — 选择镜像、启动容器、端口映射、SSH 隧道、模型下载、API 服务", "energy": 0.7, "source": "seed", "pinned": false, "dna": {}},
    {"id": "entity:gpu-monitor", "text": "GPU 监控 — nvidia-smi 实时查看、温度/功耗/显存告警、自动扩缩容策略", "energy": 0.5, "source": "seed", "pinned": false, "dna": {}},
    {"id": "hub_origin", "text": "3D 节点空间坐标(0,0,0) — 原点，所有坐标的参考基准", "energy": 0.5, "source": "hub_3d", "pinned": false, "dna": {}},
    {"id": "hub_center", "text": "3D 节点空间坐标(5,5,5) — 中心区域，高密度连接区", "energy": 0.5, "source": "hub_3d", "pinned": false, "dna": {}},
    {"id": "hub_edge", "text": "3D 节点空间坐标(10,0,0) — X 轴远端点，边缘节点", "energy": 0.5, "source": "hub_3d", "pinned": false, "dna": {}}
  ],
  "pinned": ["entity:git-pr", "entity:git-auth", "entity:git-review", "entity:wsl-setup", "entity:tdd-core", "entity:dna-extract", "entity:dna-match", "entity:dna-wormhole", "entity:debug-agent", "entity:gpu-cost"],
  "_version": 1,
  "fragments": {}
}
